titanic_testowy/__init__.py
titanic_testowy/titanic.py
titanicmg/__init__.py
titanicmg/titanic.py
titanicmg-0.0.6.dist-info/METADATA
titanicmg-0.0.6.dist-info/WHEEL
titanicmg-0.0.6.dist-info/top_level.txt
titanicmg-0.0.6.dist-info/RECORD
