Metadata-Version: 2.1
Name: titanicmg
Version: 0.0.6
Summary: Temporary pagkage for Docker testing
Home-page: UNKNOWN
Author: michlimes
Author-email: michlimes@poczta.onet.pl
License: MIT
Platform: UNKNOWN
Classifier: Programming Language :: Python
Classifier: Programming Language :: Python :: 3
Classifier: Programming Language :: Python :: 3.7
Classifier: Programming Language :: Python :: Implementation :: CPython
Classifier: Programming Language :: Python :: Implementation :: PyPy
Requires-Python: >=3.5.3
Requires-Dist: pandas (>=0.25.3)
